borealis/__init__.py
borealis/version.py
borealis-0.0.1.dist-info/DESCRIPTION.rst
borealis-0.0.1.dist-info/METADATA
borealis-0.0.1.dist-info/RECORD
borealis-0.0.1.dist-info/WHEEL
borealis-0.0.1.dist-info/metadata.json
borealis-0.0.1.dist-info/top_level.txt
