Metadata-Version: 2.0
Name: borealis
Version: 0.0.1
Summary: Fast Python
Home-page: https://github.com/yadudoc/borealis
Author: Yadu Nand Babuji
Author-email: yadudoc1729@gmail.com
License: Apache 2.0
Download-URL: https://github.com/yadudoc/borealis/archive/0.0.1.tar.gz
Keywords: Scientific computing
Platform: UNKNOWN
Classifier: Development Status :: 3 - Alpha
Classifier: Intended Audience :: Developers
Classifier: License :: OSI Approved :: Apache Software License
Classifier: Programming Language :: Python :: 3.5
Classifier: Programming Language :: Python :: 3.6
